autodevice/__init__.py
autodevice/__version__.py
autodevice/_autodevice.py
autodevice/_available_devices.py
autodevice-0.1.0.dist-info/LICENSE
autodevice-0.1.0.dist-info/METADATA
autodevice-0.1.0.dist-info/WHEEL
autodevice-0.1.0.dist-info/top_level.txt
autodevice-0.1.0.dist-info/RECORD
