Metadata-Version: 2.1
Name: autodevice
Version: 0.1.0
Summary: Automatically assign available hardware on the fly, in-line with PyTorch code.
Home-page: https://github.com/mvinyard/autodevice
Author: Michael E. Vinyard
Author-email: mvinyard.ai@gmail.com
License: MIT
Classifier: Development Status :: 2 - Pre-Alpha
Classifier: Programming Language :: Python :: 3.9
Classifier: Intended Audience :: Science/Research
Classifier: Topic :: Scientific/Engineering :: Bio-Informatics
Requires-Python: >3.9.0
License-File: LICENSE
Requires-Dist: ABCParse >=0.0.7
Requires-Dist: torch
